assemblage.py
setup.py
assemblage.egg-info/PKG-INFO
assemblage.egg-info/SOURCES.txt
assemblage.egg-info/dependency_links.txt
assemblage.egg-info/top_level.txt
assemblage.egg-info/zip-safe