Metadata-Version: 1.0
Name: assemblage
Version: 0.1
Summary: A small Python framework for building objects in dependency-injection style.
Home-page: https://github.com/pmatiello/assemblage
Author: Pedro Matiello
Author-email: pmatiello@gmail.com
License: MIT
Platform: UNKNOWN
Classifier: Programming Language :: Python
Classifier: Topic :: Software Development :: Libraries
Classifier: Intended Audience :: Developers
Classifier: Development Status :: 4 - Beta
Classifier: License :: OSI Approved :: MIT License
